{"212678499519@s.whatsapp.net":true,"212670187394@s.whatsapp.net":true,"212667219792@s.whatsapp.net":true,"212671648947@s.whatsapp.net":true,"212640148463@s.whatsapp.net":true,"212671324360@s.whatsapp.net":true,"212715243341@s.whatsapp.net":true,"212601002833@s.whatsapp.net":true,"212678080947@s.whatsapp.net":true,"212681593002@s.whatsapp.net":true,"212706680808@s.whatsapp.net":true,"212643869326@s.whatsapp.net":true,"212710025390@s.whatsapp.net":true,"212628146374@s.whatsapp.net":true,"212659209193@s.whatsapp.net":true,"212659209193:10@s.whatsapp.net":true,"212706838280@s.whatsapp.net":true,"212620858616@s.whatsapp.net":true,"212602334809@s.whatsapp.net":true,"212719377671@s.whatsapp.net":true,"212621109359@s.whatsapp.net":true,"212720616660@s.whatsapp.net":true,"212769324123@s.whatsapp.net":true,"212703890669@s.whatsapp.net":true,"212766467392@s.whatsapp.net":true,"212644073264@s.whatsapp.net":true,"212604336648@s.whatsapp.net":true,"212720015256@s.whatsapp.net":true,"212688948823@s.whatsapp.net":true,"212774366693@s.whatsapp.net":true,"212663734987@s.whatsapp.net":true,"212697024689@s.whatsapp.net":true,"212610078864@s.whatsapp.net":true,"212715053953@s.whatsapp.net":true,"212694957843@s.whatsapp.net":true,"212611521998@s.whatsapp.net":true,"212718336344@s.whatsapp.net":true,"212669457464@s.whatsapp.net":true,"212714398042@s.whatsapp.net":true,"212624661785@s.whatsapp.net":true,"212712529024@s.whatsapp.net":true,"212779513933@s.whatsapp.net":true,"212779513933:3@s.whatsapp.net":true,"212662845563@s.whatsapp.net":true,"212682559077@s.whatsapp.net":true,"212669434800@s.whatsapp.net":true,"212621355672@s.whatsapp.net":true,"212600615106@s.whatsapp.net":true,"212764725361@s.whatsapp.net":true,"212715781203@s.whatsapp.net":true,"212668987358@s.whatsapp.net":true,"212613838451@s.whatsapp.net":true,"212779277330@s.whatsapp.net":true,"212610721794@s.whatsapp.net":true,"212713382542@s.whatsapp.net":true,"212643431670@s.whatsapp.net":true,"212615778688@s.whatsapp.net":true,"212703625637@s.whatsapp.net":true,"212633963437@s.whatsapp.net":true,"212721487197@s.whatsapp.net":true,"212768980642@s.whatsapp.net":true,"212655266900@s.whatsapp.net":true,"212655266900:2@s.whatsapp.net":true,"212605662654@s.whatsapp.net":true,"212770099403@s.whatsapp.net":true,"212762850739@s.whatsapp.net":true,"212711036161@s.whatsapp.net":true,"212638707639@s.whatsapp.net":true,"212605867347@s.whatsapp.net":true,"212717824676@s.whatsapp.net":true,"212625335857@s.whatsapp.net":true,"212646148909@s.whatsapp.net":true,"212643148378@s.whatsapp.net":true,"212659860871@s.whatsapp.net":true,"212770446985@s.whatsapp.net":true,"212632824073@s.whatsapp.net":true,"212634983029@s.whatsapp.net":true,"212689846097@s.whatsapp.net":true,"212690666457@s.whatsapp.net":true,"212706635596@s.whatsapp.net":true,"212706635596:13@s.whatsapp.net":true,"212643360082@s.whatsapp.net":true,"212675166544@s.whatsapp.net":true,"212630540183@s.whatsapp.net":true,"212691341329@s.whatsapp.net":true,"212681879566@s.whatsapp.net":true,"212612040146@s.whatsapp.net":true,"212615638674@s.whatsapp.net":true,"212621040937@s.whatsapp.net":true,"212644771576@s.whatsapp.net":true,"212703451456@s.whatsapp.net":true,"212695567744@s.whatsapp.net":true,"212710675440@s.whatsapp.net":true,"212601981117@s.whatsapp.net":true,"212612941457@s.whatsapp.net":true,"212630439974@s.whatsapp.net":true,"212698537224@s.whatsapp.net":true,"212680967978@s.whatsapp.net":true,"212688112079@s.whatsapp.net":true,"212688112079:19@s.whatsapp.net":true,"212672117683@s.whatsapp.net":true,"212709884487@s.whatsapp.net":true,"212635082135@s.whatsapp.net":true,"212622819897@s.whatsapp.net":true,"212714957064@s.whatsapp.net":true,"212769884125@s.whatsapp.net":true,"212772277090@s.whatsapp.net":true,"212636611280@s.whatsapp.net":true,"212607726202@s.whatsapp.net":true,"212633201070@s.whatsapp.net":true,"212699334338@s.whatsapp.net":true,"212724051534@s.whatsapp.net":true,"212713745229@s.whatsapp.net":true,"212677188504@s.whatsapp.net":true,"212702289423@s.whatsapp.net":true,"212655631632@s.whatsapp.net":true,"212610695055@s.whatsapp.net":true,"212711990693@s.whatsapp.net":true,"212628734749@s.whatsapp.net":true,"212628734749:14@s.whatsapp.net":true,"212628734749:17@s.whatsapp.net":true,"212709608087@s.whatsapp.net":true,"212620434913@s.whatsapp.net":true,"212651608391@s.whatsapp.net":true,"212609646915@s.whatsapp.net":true,"212779362092@s.whatsapp.net":true,"212640236258@s.whatsapp.net":true,"212704272472@s.whatsapp.net":true,"212716418594@s.whatsapp.net":true,"212624474883@s.whatsapp.net":true,"212624474883:3@s.whatsapp.net":true,"212640900183@s.whatsapp.net":true,"212629649377@s.whatsapp.net":true,"212617029589@s.whatsapp.net":true,"212627078621@s.whatsapp.net":true,"212627255901@s.whatsapp.net":true,"212627768348@s.whatsapp.net":true,"212772386710@s.whatsapp.net":true,"212702972809@s.whatsapp.net":true,"212642301767@s.whatsapp.net":true,"212710664622@s.whatsapp.net":true,"212633245013@s.whatsapp.net":true,"212679257618@s.whatsapp.net":true,"212634755306@s.whatsapp.net":true,"212717138427@s.whatsapp.net":true,"212718264958@s.whatsapp.net":true,"212693028039@s.whatsapp.net":true,"212656139078@s.whatsapp.net":true,"212707561370@s.whatsapp.net":true,"212721522283@s.whatsapp.net":true,"212605686815@s.whatsapp.net":true,"212640865523@s.whatsapp.net":true,"212615537330@s.whatsapp.net":true,"212706825396@s.whatsapp.net":true,"212706825396:38@s.whatsapp.net":true,"212709332300@s.whatsapp.net":true,"212710164410@s.whatsapp.net":true,"212601275701@s.whatsapp.net":true,"212673060123@s.whatsapp.net":true,"212633314588@s.whatsapp.net":true,"212680493706@s.whatsapp.net":true,"212621969511@s.whatsapp.net":true,"212706844900@s.whatsapp.net":true,"212601883797@s.whatsapp.net":true,"212680246408@s.whatsapp.net":true,"212605206073@s.whatsapp.net":true,"212650258793@s.whatsapp.net":true,"34632872939@s.whatsapp.net":true,"212602993605@s.whatsapp.net":true,"212633490089@s.whatsapp.net":true,"212684441784@s.whatsapp.net":true,"212605760636@s.whatsapp.net":true,"212627096605@s.whatsapp.net":true,"212713414820@s.whatsapp.net":true,"212633236470@s.whatsapp.net":true,"212607463604@s.whatsapp.net":true,"212708937605@s.whatsapp.net":true,"212600736404@s.whatsapp.net":true,"212766135226@s.whatsapp.net":true,"212650023858@s.whatsapp.net":true,"212630035472@s.whatsapp.net":true,"212605255437@s.whatsapp.net":true,"212610609587@s.whatsapp.net":true,"212610609587:4@s.whatsapp.net":true,"212629063432@s.whatsapp.net":true,"212639811795@s.whatsapp.net":true,"212703307168@s.whatsapp.net":true,"212698903671@s.whatsapp.net":true,"212600812837@s.whatsapp.net":true,"212602754995@s.whatsapp.net":true,"212614284481@s.whatsapp.net":true,"212624937313@s.whatsapp.net":true,"212614652148@s.whatsapp.net":true,"212643865776@s.whatsapp.net":true,"212713123408@s.whatsapp.net":true,"212644754426@s.whatsapp.net":true,"212656322124@s.whatsapp.net":true,"212615012269@s.whatsapp.net":true,"212646286428@s.whatsapp.net":true,"212635874497@s.whatsapp.net":true,"212626414171@s.whatsapp.net":true,"212681585953@s.whatsapp.net":true,"212657940388@s.whatsapp.net":true,"212657940388:4@s.whatsapp.net":true,"212612473618@s.whatsapp.net":true,"212621771645@s.whatsapp.net":true,"212623434519@s.whatsapp.net":true,"212714115062@s.whatsapp.net":true,"212646054634@s.whatsapp.net":true,"212612609557@s.whatsapp.net":true,"212612609557:24@s.whatsapp.net":true,"212670904278@s.whatsapp.net":true,"212680561709@s.whatsapp.net":true,"212601075266@s.whatsapp.net":true,"212718172304@s.whatsapp.net":true,"212693639445@s.whatsapp.net":true,"212606480378@s.whatsapp.net":true,"212655712760@s.whatsapp.net":true,"212600448345@s.whatsapp.net":true,"212612513121@s.whatsapp.net":true,"212638123718@s.whatsapp.net":true,"212714554996@s.whatsapp.net":true,"212707419096@s.whatsapp.net":true,"212610818023@s.whatsapp.net":true,"212647983864@s.whatsapp.net":true,"212609328949@s.whatsapp.net":true,"212615601425@s.whatsapp.net":true,"212765558396@s.whatsapp.net":true,"212620390561@s.whatsapp.net":true,"212642617366@s.whatsapp.net":true,"212611543411@s.whatsapp.net":true,"212689636940@s.whatsapp.net":true,"212762911236@s.whatsapp.net":true,"212663122155@s.whatsapp.net":true,"212627741239@s.whatsapp.net":true,"212602438593@s.whatsapp.net":true,"212690976420@s.whatsapp.net":true,"212608508762@s.whatsapp.net":true,"212601627459@s.whatsapp.net":true,"212638240365@s.whatsapp.net":true,"212648636479@s.whatsapp.net":true,"212602831467@s.whatsapp.net":true,"212713314229@s.whatsapp.net":true,"212713314229:9@s.whatsapp.net":true,"212713314229:11@s.whatsapp.net":true,"212713314229:12@s.whatsapp.net":true,"212687384980@s.whatsapp.net":true,"212717019199@s.whatsapp.net":true,"212601756586@s.whatsapp.net":true,"212629568780@s.whatsapp.net":true,"212602665224@s.whatsapp.net":true,"212704356014@s.whatsapp.net":true,"212633756774@s.whatsapp.net":true,"212702515993@s.whatsapp.net":true,"212702515993:1@s.whatsapp.net":true,"212601734478@s.whatsapp.net":true,"212620776119@s.whatsapp.net":true,"212770617208@s.whatsapp.net":true,"212643411478@s.whatsapp.net":true,"212770876913@s.whatsapp.net":true,"212649083715@s.whatsapp.net":true,"212629220165@s.whatsapp.net":true,"212708519007@s.whatsapp.net":true,"212618268442@s.whatsapp.net":true,"212708501402@s.whatsapp.net":true,"212722700821@s.whatsapp.net":true,"212649117047@s.whatsapp.net":true,"212602838615@s.whatsapp.net":true,"212626371146@s.whatsapp.net":true,"212636482791@s.whatsapp.net":true,"212712251372@s.whatsapp.net":true,"212667675893@s.whatsapp.net":true,"212716469792@s.whatsapp.net":true,"212699402431@s.whatsapp.net":true,"212724598250@s.whatsapp.net":true,"212682557521@s.whatsapp.net":true,"212674166664@s.whatsapp.net":true,"212600503720@s.whatsapp.net":true,"212699743111@s.whatsapp.net":true,"212672956644@s.whatsapp.net":true,"212670598061@s.whatsapp.net":true,"212603136877@s.whatsapp.net":true,"212688064194@s.whatsapp.net":true,"212716681063@s.whatsapp.net":true,"212601634791@s.whatsapp.net":true,"212601634791:5@s.whatsapp.net":true,"212717974702@s.whatsapp.net":true,"212705819140@s.whatsapp.net":true,"212701887669@s.whatsapp.net":true,"34614298130@s.whatsapp.net":true,"212706668264@s.whatsapp.net":true,"212724117548@s.whatsapp.net":true,"212724563329@s.whatsapp.net":true,"212618308902@s.whatsapp.net":true,"212680659867@s.whatsapp.net":true,"212681894060@s.whatsapp.net":true,"212696905170@s.whatsapp.net":true,"212703492575@s.whatsapp.net":true,"212684572353@s.whatsapp.net":true,"212771077520@s.whatsapp.net":true,"212712198942@s.whatsapp.net":true,"212628360048@s.whatsapp.net":true,"212628360048:4@s.whatsapp.net":true,"212609721022@s.whatsapp.net":true,"212640071678@s.whatsapp.net":true,"212644261622@s.whatsapp.net":true,"212633875926@s.whatsapp.net":true,"212766826002@s.whatsapp.net":true,"212709505464@s.whatsapp.net":true,"212699385616@s.whatsapp.net":true,"212699385616:11@s.whatsapp.net":true,"212653554929@s.whatsapp.net":true,"212704491942@s.whatsapp.net":true,"212634640112@s.whatsapp.net":true,"212602871119@s.whatsapp.net":true,"212603973586@s.whatsapp.net":true,"212697102253@s.whatsapp.net":true,"212605505199@s.whatsapp.net":true,"212646047733@s.whatsapp.net":true,"212682918379@s.whatsapp.net":true,"212712680151@s.whatsapp.net":true,"212601374666@s.whatsapp.net":true,"212619364794@s.whatsapp.net":true,"212711835943@s.whatsapp.net":true,"212635793546@s.whatsapp.net":true,"212607795248@s.whatsapp.net":true,"212629422432@s.whatsapp.net":true,"212694537129@s.whatsapp.net":true,"212703292164@s.whatsapp.net":true,"212689381367@s.whatsapp.net":true,"212689381367:38@s.whatsapp.net":true,"212723747420@s.whatsapp.net":true,"212706448441@s.whatsapp.net":true,"212604535910@s.whatsapp.net":true,"212609322347@s.whatsapp.net":true,"212680728821@s.whatsapp.net":true,"212655483942@s.whatsapp.net":true,"212693118481@s.whatsapp.net":true,"212634756837@s.whatsapp.net":true,"212606694248@s.whatsapp.net":true,"212643546620@s.whatsapp.net":true,"212720289437@s.whatsapp.net":true,"212762804408@s.whatsapp.net":true,"212640828733@s.whatsapp.net":true,"212638536168@s.whatsapp.net":true,"212672236009@s.whatsapp.net":true,"212653803061@s.whatsapp.net":true,"212764176387@s.whatsapp.net":true,"212688556267@s.whatsapp.net":true,"212613383813@s.whatsapp.net":true,"212605776613@s.whatsapp.net":true,"212656367638@s.whatsapp.net":true,"212608970861@s.whatsapp.net":true,"212666086041@s.whatsapp.net":true,"212712374597@s.whatsapp.net":true,"212634481066@s.whatsapp.net":true,"212697121841@s.whatsapp.net":true,"212724752276@s.whatsapp.net":true,"212633129222@s.whatsapp.net":true,"212673469828@s.whatsapp.net":true,"212707770815@s.whatsapp.net":true,"212702757653@s.whatsapp.net":true,"212630882957@s.whatsapp.net":true,"212655953057@s.whatsapp.net":true,"212710508558@s.whatsapp.net":true,"212708184388@s.whatsapp.net":true,"212708184388:7@s.whatsapp.net":true,"212690100182@s.whatsapp.net":true,"212670897705@s.whatsapp.net":true,"212690191187@s.whatsapp.net":true,"212608710724@s.whatsapp.net":true,"212706603712@s.whatsapp.net":true,"212710900734@s.whatsapp.net":true,"212690213574@s.whatsapp.net":true,"212609734590@s.whatsapp.net":true,"212605354763@s.whatsapp.net":true,"212631520037@s.whatsapp.net":true,"212624291182@s.whatsapp.net":true,"212712033069@s.whatsapp.net":true,"212716951859@s.whatsapp.net":true,"212635364307@s.whatsapp.net":true,"212712562948@s.whatsapp.net":true,"212767867952@s.whatsapp.net":true,"212609266976@s.whatsapp.net":true,"212772421600@s.whatsapp.net":true,"212628118328@s.whatsapp.net":true,"212705286908@s.whatsapp.net":true,"212697495595@s.whatsapp.net":true,"212680628949@s.whatsapp.net":true,"212635391351@s.whatsapp.net":true,"212696648015@s.whatsapp.net":true,"212600314330@s.whatsapp.net":true,"212716299369@s.whatsapp.net":true,"212720706150@s.whatsapp.net":true,"212707216916@s.whatsapp.net":true,"212709758886@s.whatsapp.net":true,"212695381236@s.whatsapp.net":true,"212633810225@s.whatsapp.net":true,"212777389662@s.whatsapp.net":true,"212713167930@s.whatsapp.net":true,"212617159833@s.whatsapp.net":true,"212781709197@s.whatsapp.net":true,"212655608758@s.whatsapp.net":true,"212779383380@s.whatsapp.net":true,"212771377633@s.whatsapp.net":true,"212771377633:20@s.whatsapp.net":true,"212636143947@s.whatsapp.net":true,"212695520020@s.whatsapp.net":true,"212702876170@s.whatsapp.net":true,"212723810379@s.whatsapp.net":true,"212772150010@s.whatsapp.net":true,"212618983715@s.whatsapp.net":true,"212646146690@s.whatsapp.net":true,"212702572616@s.whatsapp.net":true,"212609479994@s.whatsapp.net":true,"212772239328@s.whatsapp.net":true,"212705480067@s.whatsapp.net":true,"212666109930@s.whatsapp.net":true,"212680488802@s.whatsapp.net":true,"212720098360@s.whatsapp.net":true,"212646287243@s.whatsapp.net":true,"212710548473@s.whatsapp.net":true,"212708500634@s.whatsapp.net":true,"212617426769@s.whatsapp.net":true,"212625433141@s.whatsapp.net":true,"212637662869@s.whatsapp.net":true,"212650957044@s.whatsapp.net":true,"212716279588@s.whatsapp.net":true,"212712820428@s.whatsapp.net":true,"212721750687@s.whatsapp.net":true,"212716346671@s.whatsapp.net":true,"212650384761@s.whatsapp.net":true,"212633718411@s.whatsapp.net":true,"212695391012@s.whatsapp.net":true,"212630591278@s.whatsapp.net":true,"212664699025@s.whatsapp.net":true,"212699020511@s.whatsapp.net":true,"212632782931@s.whatsapp.net":true,"212602569071@s.whatsapp.net":true,"212642404019@s.whatsapp.net":true,"212607414493@s.whatsapp.net":true,"212679547957@s.whatsapp.net":true,"212770692813@s.whatsapp.net":true,"212657464882@s.whatsapp.net":true,"212699450279@s.whatsapp.net":true,"212609018578@s.whatsapp.net":true,"212622797133@s.whatsapp.net":true,"212777066024@s.whatsapp.net":true,"212709445030@s.whatsapp.net":true,"212669661436@s.whatsapp.net":true,"212660799008@s.whatsapp.net":true,"212703320380@s.whatsapp.net":true,"212703320380:1@s.whatsapp.net":true,"212687232701@s.whatsapp.net":true,"212715402623@s.whatsapp.net":true,"212603370497@s.whatsapp.net":true,"212773252442@s.whatsapp.net":true,"212704604322@s.whatsapp.net":true,"212700613150@s.whatsapp.net":true,"212633674669@s.whatsapp.net":true,"212651956749@s.whatsapp.net":true,"212668525231@s.whatsapp.net":true,"212647294300@s.whatsapp.net":true,"212639592749@s.whatsapp.net":true,"212682243708@s.whatsapp.net":true,"212720827773@s.whatsapp.net":true,"212709708749@s.whatsapp.net":true,"212702429330@s.whatsapp.net":true,"212684484413@s.whatsapp.net":true,"212605888545@s.whatsapp.net":true,"212666016195@s.whatsapp.net":true,"212615662461@s.whatsapp.net":true,"212713787195@s.whatsapp.net":true,"212700518346@s.whatsapp.net":true,"212682910946@s.whatsapp.net":true,"212630605747@s.whatsapp.net":true,"212628849088@s.whatsapp.net":true,"212720509532@s.whatsapp.net":true,"212681539889@s.whatsapp.net":true,"212622468131@s.whatsapp.net":true,"212627719903@s.whatsapp.net":true,"212603378366@s.whatsapp.net":true,"212718499301@s.whatsapp.net":true,"212764036160@s.whatsapp.net":true,"212652019872@s.whatsapp.net":true,"212604673652@s.whatsapp.net":true,"212635737150@s.whatsapp.net":true,"212778506531@s.whatsapp.net":true,"212619425274@s.whatsapp.net":true,"212619425274:57@s.whatsapp.net":true,"212619425274:58@s.whatsapp.net":true,"212711916595@s.whatsapp.net":true,"212602953823@s.whatsapp.net":true,"212650857182@s.whatsapp.net":true,"212602304374@s.whatsapp.net":true,"212616827920@s.whatsapp.net":true,"212718100308@s.whatsapp.net":true,"212646414294@s.whatsapp.net":true,"212641553793@s.whatsapp.net":true,"212666473715@s.whatsapp.net":true,"31687252392@s.whatsapp.net":true,"212674678465@s.whatsapp.net":true,"212655319157@s.whatsapp.net":true,"255718952450@s.whatsapp.net":true,"212656741629@s.whatsapp.net":true,"212705131787@s.whatsapp.net":true,"212706083644@s.whatsapp.net":true,"212684208984@s.whatsapp.net":true,"212605407208@s.whatsapp.net":true,"212636528049@s.whatsapp.net":true,"212690610756@s.whatsapp.net":true,"212702495754@s.whatsapp.net":true,"212719194691@s.whatsapp.net":true,"212773373618@s.whatsapp.net":true,"212714203824@s.whatsapp.net":true,"212714203824:8@s.whatsapp.net":true,"212722954236@s.whatsapp.net":true,"212687236165@s.whatsapp.net":true,"212702884068@s.whatsapp.net":true,"212611998895@s.whatsapp.net":true,"212675085699@s.whatsapp.net":true,"212646951881@s.whatsapp.net":true,"212716351592@s.whatsapp.net":true,"212606201946@s.whatsapp.net":true,"212629413851@s.whatsapp.net":true,"212673383543@s.whatsapp.net":true,"212774339343@s.whatsapp.net":true,"212606750046@s.whatsapp.net":true,"212606750046:1@s.whatsapp.net":true,"212642464905@s.whatsapp.net":true,"212641039421@s.whatsapp.net":true,"212646290597@s.whatsapp.net":true,"212609906453@s.whatsapp.net":true,"212675907439@s.whatsapp.net":true,"212605564001@s.whatsapp.net":true,"212618326270@s.whatsapp.net":true,"212716616998@s.whatsapp.net":true,"6283151441957@s.whatsapp.net":true,"212695108886@s.whatsapp.net":true,"212721528415@s.whatsapp.net":true,"212602775765@s.whatsapp.net":true,"212636406900@s.whatsapp.net":true,"212622235251@s.whatsapp.net":true,"212699456739@s.whatsapp.net":true,"212641851601@s.whatsapp.net":true,"212620323355@s.whatsapp.net":true,"212636079040@s.whatsapp.net":true,"212659603294@s.whatsapp.net":true,"212719861997@s.whatsapp.net":true,"212616238774@s.whatsapp.net":true,"212647514172@s.whatsapp.net":true,"212700290821@s.whatsapp.net":true,"212706165232@s.whatsapp.net":true,"212666196029@s.whatsapp.net":true,"212763382690@s.whatsapp.net":true,"212712290328@s.whatsapp.net":true,"212700651869@s.whatsapp.net":true,"212723943420@s.whatsapp.net":true,"212704598685@s.whatsapp.net":true,"212600136318@s.whatsapp.net":true,"212605270769@s.whatsapp.net":true,"212709280091@s.whatsapp.net":true,"212601092742@s.whatsapp.net":true,"212638681731@s.whatsapp.net":true,"212711928901@s.whatsapp.net":true,"212766678240@s.whatsapp.net":true,"212703923076@s.whatsapp.net":true,"212616200955@s.whatsapp.net":true,"212644104120@s.whatsapp.net":true,"212644104120:12@s.whatsapp.net":true,"212632589399@s.whatsapp.net":true,"212622560296@s.whatsapp.net":true,"212709620973@s.whatsapp.net":true,"212767804595@s.whatsapp.net":true,"212623045604@s.whatsapp.net":true,"212665789442@s.whatsapp.net":true,"212627746304@s.whatsapp.net":true,"212706568156@s.whatsapp.net":true,"212620047794@s.whatsapp.net":true,"212706756409@s.whatsapp.net":true,"212684261407@s.whatsapp.net":true,"212719176374@s.whatsapp.net":true,"212774755444@s.whatsapp.net":true,"212722425890@s.whatsapp.net":true,"212624732332@s.whatsapp.net":true,"212696962016@s.whatsapp.net":true,"212630124126@s.whatsapp.net":true,"212627427903@s.whatsapp.net":true,"212612049219@s.whatsapp.net":true,"212643833781@s.whatsapp.net":true,"212613279881@s.whatsapp.net":true,"212658250054@s.whatsapp.net":true,"212696463239@s.whatsapp.net":true,"212709882497@s.whatsapp.net":true,"212678088097@s.whatsapp.net":true,"212702838196@s.whatsapp.net":true,"212637288799@s.whatsapp.net":true,"212637288799:2@s.whatsapp.net":true,"212770922776@s.whatsapp.net":true,"212716056000@s.whatsapp.net":true,"212691337948@s.whatsapp.net":true,"212630035012@s.whatsapp.net":true,"212653970799@s.whatsapp.net":true,"212611963253@s.whatsapp.net":true,"212665931505@s.whatsapp.net":true,"212665931505:1@s.whatsapp.net":true,"212714473169@s.whatsapp.net":true,"212697009305@s.whatsapp.net":true,"212611748539@s.whatsapp.net":true,"212607568673@s.whatsapp.net":true,"212714234481@s.whatsapp.net":true,"212627270399@s.whatsapp.net":true,"212608708985@s.whatsapp.net":true,"212637978007@s.whatsapp.net":true,"212657332283@s.whatsapp.net":true,"212704696440@s.whatsapp.net":true,"212622797590@s.whatsapp.net":true,"212644291331@s.whatsapp.net":true,"212702519703@s.whatsapp.net":true,"212657340943@s.whatsapp.net":true,"212695020393@s.whatsapp.net":true,"212621481728@s.whatsapp.net":true,"212621481728:24@s.whatsapp.net":true,"212621481728:27@s.whatsapp.net":true,"212617177499@s.whatsapp.net":true,"212602690753@s.whatsapp.net":true,"212708643011@s.whatsapp.net":true,"212776396689@s.whatsapp.net":true,"212617602848@s.whatsapp.net":true,"212608653015@s.whatsapp.net":true,"212620603515@s.whatsapp.net":true,"212606715703@s.whatsapp.net":true,"212681684498@s.whatsapp.net":true,"212637138784@s.whatsapp.net":true,"212700652541@s.whatsapp.net":true,"212669506887@s.whatsapp.net":true,"212641485660@s.whatsapp.net":true,"212691174452@s.whatsapp.net":true,"212697343786@s.whatsapp.net":true,"212713469333@s.whatsapp.net":true,"212723344142@s.whatsapp.net":true,"212656170578@s.whatsapp.net":true,"212702454499@s.whatsapp.net":true,"212629923395@s.whatsapp.net":true,"212697809523@s.whatsapp.net":true,"212697809523:71@s.whatsapp.net":true,"212699361777@s.whatsapp.net":true,"212714755679@s.whatsapp.net":true,"212704208938@s.whatsapp.net":true,"212639693310@s.whatsapp.net":true,"22248741079@s.whatsapp.net":true,"212684060189@s.whatsapp.net":true,"212665995741@s.whatsapp.net":true,"212665995741:1@s.whatsapp.net":true,"212652373298@s.whatsapp.net":true,"212711802241@s.whatsapp.net":true,"212709195218@s.whatsapp.net":true,"212605928311@s.whatsapp.net":true,"212710344878@s.whatsapp.net":true,"212680876848@s.whatsapp.net":true,"212619333698@s.whatsapp.net":true,"212700453319@s.whatsapp.net":true,"212698046360@s.whatsapp.net":true,"212603686788@s.whatsapp.net":true,"212723611302@s.whatsapp.net":true,"212689976468@s.whatsapp.net":true,"212699477189@s.whatsapp.net":true,"212720161523@s.whatsapp.net":true,"212605937656@s.whatsapp.net":true,"212629074687@s.whatsapp.net":true,"212615728878@s.whatsapp.net":true,"212702401358@s.whatsapp.net":true,"212605365790@s.whatsapp.net":true,"212637886159@s.whatsapp.net":true,"212637886159:3@s.whatsapp.net":true,"212669183159@s.whatsapp.net":true,"212609022252@s.whatsapp.net":true,"212702901969@s.whatsapp.net":true,"212711856783@s.whatsapp.net":true,"212711856783:16@s.whatsapp.net":true,"212701746408@s.whatsapp.net":true,"212630963757@s.whatsapp.net":true,"212629416289@s.whatsapp.net":true,"212622903305@s.whatsapp.net":true,"212659924223@s.whatsapp.net":true,"212659924223:8@s.whatsapp.net":true,"212659393041@s.whatsapp.net":true,"212644844787@s.whatsapp.net":true,"212691824030@s.whatsapp.net":true,"212724407192@s.whatsapp.net":true,"212668995530@s.whatsapp.net":true,"212616866248@s.whatsapp.net":true,"212693012532@s.whatsapp.net":true,"212710604332@s.whatsapp.net":true,"212712367487@s.whatsapp.net":true,"212635970415@s.whatsapp.net":true,"212615091216@s.whatsapp.net":true,"212680702093@s.whatsapp.net":true,"212708965633@s.whatsapp.net":true,"212750709229@s.whatsapp.net":true,"27815243509@s.whatsapp.net":true,"212720759871@s.whatsapp.net":true,"212627081817@s.whatsapp.net":true,"212709745619@s.whatsapp.net":true,"212644986542@s.whatsapp.net":true,"212706193568@s.whatsapp.net":true,"212713498032@s.whatsapp.net":true,"212602997647@s.whatsapp.net":true,"212635077884@s.whatsapp.net":true,"212630572072@s.whatsapp.net":true,"212676576768@s.whatsapp.net":true,"212676576768:23@s.whatsapp.net":true,"212676576768:28@s.whatsapp.net":true,"212679326049@s.whatsapp.net":true,"212615248681@s.whatsapp.net":true,"212673242460@s.whatsapp.net":true,"212702987784@s.whatsapp.net":true,"212654364906@s.whatsapp.net":true,"212631914746@s.whatsapp.net":true,"212631914746:9@s.whatsapp.net":true,"212609846230@s.whatsapp.net":true,"212710586979@s.whatsapp.net":true,"212711645127@s.whatsapp.net":true,"212602529178@s.whatsapp.net":true,"212706231298@s.whatsapp.net":true,"212633711001@s.whatsapp.net":true,"212624412336@s.whatsapp.net":true,"212718136989@s.whatsapp.net":true,"212705960204@s.whatsapp.net":true,"212717960789@s.whatsapp.net":true,"212693326526@s.whatsapp.net":true,"212649511744@s.whatsapp.net":true,"212718287086@s.whatsapp.net":true,"212612299064@s.whatsapp.net":true,"212606636471@s.whatsapp.net":true,"212630954069@s.whatsapp.net":true,"212770315786@s.whatsapp.net":true,"212615488697@s.whatsapp.net":true,"212643041137@s.whatsapp.net":true,"212716119527@s.whatsapp.net":true,"212678435294@s.whatsapp.net":true,"212687383072@s.whatsapp.net":true,"212702580477@s.whatsapp.net":true,"212713462203@s.whatsapp.net":true,"212681559328@s.whatsapp.net":true,"212681039991@s.whatsapp.net":true,"212601798146@s.whatsapp.net":true,"212681397457@s.whatsapp.net":true,"212760360305@s.whatsapp.net":true,"212614801879@s.whatsapp.net":true,"212682305946@s.whatsapp.net":true,"212722109653@s.whatsapp.net":true,"212708627223@s.whatsapp.net":true,"212711313890@s.whatsapp.net":true,"212771922955@s.whatsapp.net":true,"212638492718@s.whatsapp.net":true,"212710530971@s.whatsapp.net":true,"212624133278@s.whatsapp.net":true,"212721034737@s.whatsapp.net":true,"212715327384@s.whatsapp.net":true,"212676956515@s.whatsapp.net":true,"212722173598@s.whatsapp.net":true,"212601253216@s.whatsapp.net":true,"212682802101@s.whatsapp.net":true,"212669859310@s.whatsapp.net":true,"212605177828@s.whatsapp.net":true,"212705840792@s.whatsapp.net":true,"212703632313@s.whatsapp.net":true,"212710516870@s.whatsapp.net":true,"212677745173@s.whatsapp.net":true,"212711237849@s.whatsapp.net":true,"212619582889@s.whatsapp.net":true,"212667325465@s.whatsapp.net":true,"212656804008@s.whatsapp.net":true,"212656804008:15@s.whatsapp.net":true,"212695327641@s.whatsapp.net":true,"212702578449@s.whatsapp.net":true,"212614151813@s.whatsapp.net":true,"212679498698@s.whatsapp.net":true,"212714144802@s.whatsapp.net":true,"212707332199@s.whatsapp.net":true,"212716711153@s.whatsapp.net":true,"212623037337@s.whatsapp.net":true,"212607389955@s.whatsapp.net":true,"212723829332@s.whatsapp.net":true,"212640137519@s.whatsapp.net":true,"212722307735@s.whatsapp.net":true,"212604807556@s.whatsapp.net":true,"212706786264@s.whatsapp.net":true,"212605394373@s.whatsapp.net":true,"212646831392@s.whatsapp.net":true,"212636650994@s.whatsapp.net":true,"212628976538@s.whatsapp.net":true,"212617025347@s.whatsapp.net":true,"212711822139@s.whatsapp.net":true,"212604259177@s.whatsapp.net":true,"212632606703@s.whatsapp.net":true,"212645934552@s.whatsapp.net":true,"212698062403@s.whatsapp.net":true,"212698062403:41@s.whatsapp.net":true,"212698062403:46@s.whatsapp.net":true,"212675731329@s.whatsapp.net":true,"212723929411@s.whatsapp.net":true,"212717621047@s.whatsapp.net":true,"447898552950@s.whatsapp.net":true,"212646100978@s.whatsapp.net":true,"212724209410@s.whatsapp.net":true,"212655121457@s.whatsapp.net":true,"212708685033@s.whatsapp.net":true,"212607339693@s.whatsapp.net":true,"212690229217@s.whatsapp.net":true,"212705919607@s.whatsapp.net":true,"212719078354@s.whatsapp.net":true,"212707728900@s.whatsapp.net":true,"212766673641@s.whatsapp.net":true,"212624092106@s.whatsapp.net":true,"212608228594@s.whatsapp.net":true,"212704142418@s.whatsapp.net":true,"447424333185@s.whatsapp.net":true,"212698650774@s.whatsapp.net":true,"212713980360@s.whatsapp.net":true,"212713472115@s.whatsapp.net":true,"212768136297@s.whatsapp.net":true,"212701229814@s.whatsapp.net":true,"93745049643@s.whatsapp.net":true,"212676252571@s.whatsapp.net":true,"212681096501@s.whatsapp.net":true,"212620223237@s.whatsapp.net":true,"212627394524@s.whatsapp.net":true,"212723467835@s.whatsapp.net":true,"212602687486@s.whatsapp.net":true,"212677357983@s.whatsapp.net":true,"212615234394@s.whatsapp.net":true,"212700279172@s.whatsapp.net":true,"212699367131@s.whatsapp.net":true,"212613648891@s.whatsapp.net":true,"212775388897@s.whatsapp.net":true,"212630804224@s.whatsapp.net":true,"212678838777@s.whatsapp.net":true,"212638242370@s.whatsapp.net":true,"212681421021@s.whatsapp.net":true,"212714140617@s.whatsapp.net":true,"212679735205@s.whatsapp.net":true,"212770475485@s.whatsapp.net":true,"212778816768@s.whatsapp.net":true,"212776334744@s.whatsapp.net":true,"212607934833@s.whatsapp.net":true,"212619044690@s.whatsapp.net":true,"212720567859@s.whatsapp.net":true,"212682892650@s.whatsapp.net":true,"212712370869@s.whatsapp.net":true,"212616674129@s.whatsapp.net":true,"212721092659@s.whatsapp.net":true,"212635122720@s.whatsapp.net":true,"212633096991@s.whatsapp.net":true,"212634336847@s.whatsapp.net":true,"212720526289@s.whatsapp.net":true,"212644041368@s.whatsapp.net":true,"212761776817@s.whatsapp.net":true,"212623455074@s.whatsapp.net":true,"212600417283@s.whatsapp.net":true,"212698590622@s.whatsapp.net":true,"212635922891@s.whatsapp.net":true,"212717281622@s.whatsapp.net":true,"212621467469@s.whatsapp.net":true,"212600297546@s.whatsapp.net":true,"212716274004@s.whatsapp.net":true,"212682339033@s.whatsapp.net":true,"212681252140@s.whatsapp.net":true,"212606138712@s.whatsapp.net":true,"212640358032@s.whatsapp.net":true,"212722421119@s.whatsapp.net":true,"212722421119:2@s.whatsapp.net":true,"212779788821@s.whatsapp.net":true,"212712149070@s.whatsapp.net":true,"212776611230@s.whatsapp.net":true,"212696798822@s.whatsapp.net":true,"212717453428@s.whatsapp.net":true,"212616488164@s.whatsapp.net":true,"212629264844@s.whatsapp.net":true,"212610259909@s.whatsapp.net":true,"212658941535@s.whatsapp.net":true,"212723718553@s.whatsapp.net":true,"212767278494@s.whatsapp.net":true,"212646450317@s.whatsapp.net":true,"212678235612@s.whatsapp.net":true,"212706561940@s.whatsapp.net":true,"212710369980@s.whatsapp.net":true,"212635774908@s.whatsapp.net":true,"212773349881@s.whatsapp.net":true,"212602251713@s.whatsapp.net":true,"212762958238@s.whatsapp.net":true,"212711834566@s.whatsapp.net":true,"14379830492@s.whatsapp.net":true,"212716929421@s.whatsapp.net":true,"212651689886@s.whatsapp.net":true,"212651689886:4@s.whatsapp.net":true,"212719254023@s.whatsapp.net":true,"212690183581@s.whatsapp.net":true,"212609381170@s.whatsapp.net":true,"212719227867@s.whatsapp.net":true,"212705096140@s.whatsapp.net":true,"212601464659@s.whatsapp.net":true,"212641451588@s.whatsapp.net":true,"212640123752@s.whatsapp.net":true,"212606349914@s.whatsapp.net":true,"212708643814@s.whatsapp.net":true,"212640435342@s.whatsapp.net":true,"212719914396@s.whatsapp.net":true,"212723730765@s.whatsapp.net":true,"212723730765:2@s.whatsapp.net":true,"212629077782@s.whatsapp.net":true,"212648505733@s.whatsapp.net":true,"212614718642@s.whatsapp.net":true,"212626961359@s.whatsapp.net":true,"212707074577@s.whatsapp.net":true,"212668049372@s.whatsapp.net":true,"212629531705@s.whatsapp.net":true,"212629531705:9@s.whatsapp.net":true,"212603986638@s.whatsapp.net":true,"212722130931@s.whatsapp.net":true,"212646654171@s.whatsapp.net":true,"212718474985@s.whatsapp.net":true,"212674750939@s.whatsapp.net":true,"212644244091@s.whatsapp.net":true,"212614169519@s.whatsapp.net":true,"212614169519:18@s.whatsapp.net":true,"212657765484@s.whatsapp.net":true,"212602769810@s.whatsapp.net":true,"212709470318@s.whatsapp.net":true,"212711501222@s.whatsapp.net":true,"212700560531@s.whatsapp.net":true,"212618245105@s.whatsapp.net":true,"212642937951@s.whatsapp.net":true,"212610717583@s.whatsapp.net":true,"212666745527@s.whatsapp.net":true,"212670969716@s.whatsapp.net":true,"212722009834@s.whatsapp.net":true,"212694104087@s.whatsapp.net":true,"212623785741@s.whatsapp.net":true,"212615811960@s.whatsapp.net":true,"212601593897@s.whatsapp.net":true,"212667453941@s.whatsapp.net":true,"212708189978@s.whatsapp.net":true,"212633316997@s.whatsapp.net":true,"212710027186@s.whatsapp.net":true,"212670772844@s.whatsapp.net":true,"212704504123@s.whatsapp.net":true,"212652531844@s.whatsapp.net":true,"212634493022@s.whatsapp.net":true,"212671207303@s.whatsapp.net":true,"212651101979@s.whatsapp.net":true,"212776517052@s.whatsapp.net":true,"212698985839@s.whatsapp.net":true,"212617698669@s.whatsapp.net":true,"212722318559@s.whatsapp.net":true,"212606626760@s.whatsapp.net":true,"212718173652@s.whatsapp.net":true,"212700190132@s.whatsapp.net":true,"212659216428@s.whatsapp.net":true,"212637207050@s.whatsapp.net":true,"212665127693@s.whatsapp.net":true,"212635291758@s.whatsapp.net":true,"212613994964@s.whatsapp.net":true,"212771905132@s.whatsapp.net":true,"212627615812@s.whatsapp.net":true,"212654216848@s.whatsapp.net":true,"212693349601@s.whatsapp.net":true,"212717681016@s.whatsapp.net":true,"212716549428@s.whatsapp.net":true,"212622416645@s.whatsapp.net":true,"212657145715@s.whatsapp.net":true,"212608453867@s.whatsapp.net":true,"212681389799@s.whatsapp.net":true,"212635460799@s.whatsapp.net":true,"212622657928@s.whatsapp.net":true,"212670846710@s.whatsapp.net":true,"212619937955@s.whatsapp.net":true,"212608217343@s.whatsapp.net":true,"212659746559@s.whatsapp.net":true,"212638958559@s.whatsapp.net":true,"212613791063@s.whatsapp.net":true,"212601941653@s.whatsapp.net":true,"212602558944@s.whatsapp.net":true,"212693753344@s.whatsapp.net":true,"212693753344:8@s.whatsapp.net":true,"212653544715@s.whatsapp.net":true,"212666545710@s.whatsapp.net":true,"212679731591@s.whatsapp.net":true,"212707585737@s.whatsapp.net":true,"212707585737:2@s.whatsapp.net":true,"212646768033@s.whatsapp.net":true,"212602025893@s.whatsapp.net":true,"212698593759@s.whatsapp.net":true,"212763594212@s.whatsapp.net":true,"212603624898@s.whatsapp.net":true,"212777021089@s.whatsapp.net":true,"212662558433@s.whatsapp.net":true,"212604572822@s.whatsapp.net":true,"212704362850@s.whatsapp.net":true,"212602304970@s.whatsapp.net":true,"212662445250@s.whatsapp.net":true,"212625793380@s.whatsapp.net":true,"212605571246@s.whatsapp.net":true,"212614129133@s.whatsapp.net":true,"212777377060@s.whatsapp.net":true,"212718101332@s.whatsapp.net":true,"212699214777@s.whatsapp.net":true,"212646761322@s.whatsapp.net":true,"212627479992@s.whatsapp.net":true,"212603850919@s.whatsapp.net":true,"212659712777@s.whatsapp.net":true,"212720983335@s.whatsapp.net":true,"212710119299@s.whatsapp.net":true,"212624326718@s.whatsapp.net":true,"212608838563@s.whatsapp.net":true,"212635612135@s.whatsapp.net":true,"212646779687@s.whatsapp.net":true,"212777859270@s.whatsapp.net":true,"212715416000@s.whatsapp.net":true,"212709374928@s.whatsapp.net":true,"212710244254@s.whatsapp.net":true,"212606318623@s.whatsapp.net":true,"212612778663@s.whatsapp.net":true,"212650266672@s.whatsapp.net":true,"212678832240@s.whatsapp.net":true,"905389434062@s.whatsapp.net":true,"212767830506@s.whatsapp.net":true,"212712275152@s.whatsapp.net":true,"34604861326@s.whatsapp.net":true,"212721199844@s.whatsapp.net":true,"212706032422@s.whatsapp.net":true,"212706032422:16@s.whatsapp.net":true,"212773337815@s.whatsapp.net":true,"212601616980@s.whatsapp.net":true,"212604234888@s.whatsapp.net":true,"212634974909@s.whatsapp.net":true,"212604812953@s.whatsapp.net":true,"212680783744@s.whatsapp.net":true,"212687488282@s.whatsapp.net":true,"212605721925@s.whatsapp.net":true,"212652101902@s.whatsapp.net":true,"212710616493@s.whatsapp.net":true,"212607875370@s.whatsapp.net":true,"212690358923@s.whatsapp.net":true,"212716108402@s.whatsapp.net":true,"212778644265@s.whatsapp.net":true,"212638102012@s.whatsapp.net":true,"212778432597@s.whatsapp.net":true,"212773301202@s.whatsapp.net":true,"212658261018@s.whatsapp.net":true,"212664575458@s.whatsapp.net":true,"212653776349@s.whatsapp.net":true,"212762390841@s.whatsapp.net":true,"212667573775@s.whatsapp.net":true,"212641455365@s.whatsapp.net":true,"212697829519@s.whatsapp.net":true,"212697829519:2@s.whatsapp.net":true,"212709260067@s.whatsapp.net":true,"212610712982@s.whatsapp.net":true,"212690462957@s.whatsapp.net":true,"212629138356@s.whatsapp.net":true,"212630320707@s.whatsapp.net":true,"212653573024@s.whatsapp.net":true}